{
 "kanda": 2,
 "sarga": 9,
 "voice": "divya",
 "file": "2-9.opus",
 "dur": 1006.75,
 "verses": [
  {
   "v": 1,
   "t": 0.0
  },
  {
   "v": 2,
   "t": 11.73
  },
  {
   "v": 3,
   "t": 22.5
  },
  {
   "v": 4,
   "t": 43.82
  },
  {
   "v": 5,
   "t": 56.89
  },
  {
   "v": 6,
   "t": 69.84
  },
  {
   "v": 7,
   "t": 90.71
  },
  {
   "v": 8,
   "t": 103.01
  },
  {
   "v": 9,
   "t": 112.3
  },
  {
   "v": 10,
   "t": 123.7
  },
  {
   "v": 11,
   "t": 134.7
  },
  {
   "v": 12,
   "t": 148.06,
   "to": 13
  },
  {
   "v": 14,
   "t": 181.01
  },
  {
   "v": 15,
   "t": 192.5
  },
  {
   "v": 16,
   "t": 207.01
  },
  {
   "v": 17,
   "t": 230.59,
   "to": 18
  },
  {
   "v": 19,
   "t": 264.56
  },
  {
   "v": 20,
   "t": 279.34
  },
  {
   "v": 21,
   "t": 293.42
  },
  {
   "v": 22,
   "t": 308.25
  },
  {
   "v": 23,
   "t": 319.99
  },
  {
   "v": 24,
   "t": 333.21
  },
  {
   "v": 25,
   "t": 345.75
  },
  {
   "v": 26,
   "t": 361.95
  },
  {
   "v": 27,
   "t": 371.99
  },
  {
   "v": 28,
   "t": 386.0
  },
  {
   "v": 29,
   "t": 404.16
  },
  {
   "v": 30,
   "t": 419.27
  },
  {
   "v": 31,
   "t": 433.53
  },
  {
   "v": 32,
   "t": 452.34
  },
  {
   "v": 33,
   "t": 469.61
  },
  {
   "v": 34,
   "t": 484.0
  },
  {
   "v": 35,
   "t": 494.15
  },
  {
   "v": 36,
   "t": 522.08,
   "to": 37
  },
  {
   "v": 38,
   "t": 557.41,
   "to": 39
  },
  {
   "v": 40,
   "t": 583.39
  },
  {
   "v": 41,
   "t": 601.66
  },
  {
   "v": 42,
   "t": 619.87
  },
  {
   "v": 43,
   "t": 639.6
  },
  {
   "v": 44,
   "t": 654.37
  },
  {
   "v": 45,
   "t": 676.6,
   "to": 46
  },
  {
   "v": 47,
   "t": 708.99,
   "to": 48
  },
  {
   "v": 49,
   "t": 733.34,
   "to": 50
  },
  {
   "v": 51,
   "t": 750.86
  },
  {
   "v": 52,
   "t": 767.31
  },
  {
   "v": 53,
   "t": 781.35
  },
  {
   "v": 54,
   "t": 793.43
  },
  {
   "v": 55,
   "t": 817.45,
   "to": 56
  },
  {
   "v": 57,
   "t": 841.08
  },
  {
   "v": 58,
   "t": 852.68,
   "to": 59
  },
  {
   "v": 60,
   "t": 882.76
  },
  {
   "v": 61,
   "t": 898.95
  },
  {
   "v": 62,
   "t": 916.84
  },
  {
   "v": 63,
   "t": 934.76
  },
  {
   "v": 64,
   "t": 950.68
  },
  {
   "v": 65,
   "t": 969.72
  },
  {
   "v": 66,
   "t": 986.54
  }
 ]
}